CHANGES.txt
MANIFEST.in
README.rst
setup.cfg
setup.py
pyramid_ipauth/__init__.py
pyramid_ipauth/tests.py
pyramid_ipauth/utils.py
pyramid_ipauth.egg-info/PKG-INFO
pyramid_ipauth.egg-info/SOURCES.txt
pyramid_ipauth.egg-info/dependency_links.txt
pyramid_ipauth.egg-info/not-zip-safe
pyramid_ipauth.egg-info/requires.txt
pyramid_ipauth.egg-info/top_level.txt