Metadata-Version: 1.1
Name: pyramid-ipauth
Version: 0.3.2
Summary: pyramid_ipauth
Home-page: https://github.com/mozilla-services/pyramid_ipauth
Author: Mozilla Services
Author-email: services-dev@mozilla.org
License: UNKNOWN
Keywords: web pyramid pylons authentication
Platform: UNKNOWN
Classifier: Programming Language :: Python
Classifier: Framework :: Pylons
Classifier: Topic :: Internet :: WWW/HTTP
Classifier: Programming Language :: Python
Classifier: Programming Language :: Python :: 2.6
Classifier: Programming Language :: Python :: 2.7
Classifier: Programming Language :: Python :: 3.1
Classifier: Programming Language :: Python :: 3.2
Classifier: Programming Language :: Python :: 3.3
Classifier: Programming Language :: Python :: 3.4
Classifier: Programming Language :: Python :: 3.5
